livekit/plugins/wuba/__init__.py
livekit/plugins/wuba/dify.py
livekit/plugins/wuba/log.py
livekit/plugins/wuba/models.py
livekit/plugins/wuba/py.typed
livekit/plugins/wuba/stt.py
livekit/plugins/wuba/tts.py
livekit/plugins/wuba/turn_detector.py
livekit/plugins/wuba/utils.py
livekit/plugins/wuba/version.py
livekit/plugins/wuba/silero/__init__.py
livekit/plugins/wuba/silero/log.py
livekit/plugins/wuba/silero/onnx_model.py
livekit/plugins/wuba/silero/py.typed
livekit/plugins/wuba/silero/vad.py
livekit/plugins/wuba/silero/resources/__init__.py
livekit/plugins/wuba/silero/resources/silero_vad.onnx
livekit_plugins_wuba-1.3.0.dist-info/METADATA
livekit_plugins_wuba-1.3.0.dist-info/WHEEL
livekit_plugins_wuba-1.3.0.dist-info/RECORD
