Metadata-Version: 2.4
Name: livekit-plugins-wuba
Version: 1.3.0
Summary: LiveKit Agents Plugin for 58-LBG voice server
Author-email: wangmengdi <wangmengdi@58.com>
Keywords: audio,livekit,realtime,video,webrtc
Classifier: Intended Audience :: Developers
Classifier: Programming Language :: Python :: 3
Classifier: Programming Language :: Python :: 3 :: Only
Classifier: Programming Language :: Python :: 3.9
Classifier: Programming Language :: Python :: 3.10
Classifier: Topic :: Multimedia :: Sound/Audio
Classifier: Topic :: Multimedia :: Video
Classifier: Topic :: Scientific/Engineering :: Artificial Intelligence
Requires-Python: >=3.10
Requires-Dist: jinja2>=3.1.6
Requires-Dist: livekit-agents==1.2.9
Requires-Dist: numpy>=1.26.4
Requires-Dist: onnxruntime>=1.20.1
Requires-Dist: osc-data>=0.1.7
Requires-Dist: pydantic>=2.0
Requires-Dist: python-dotenv>=0.9.9
Requires-Dist: requests>=2.32.3
Requires-Dist: transformers>=4.55.0
